example_pkg/__init__.py
example_pkg/help.py
example_pkg_zzy-0.0.2.dist-info/DESCRIPTION.rst
example_pkg_zzy-0.0.2.dist-info/METADATA
example_pkg_zzy-0.0.2.dist-info/RECORD
example_pkg_zzy-0.0.2.dist-info/WHEEL
example_pkg_zzy-0.0.2.dist-info/metadata.json
example_pkg_zzy-0.0.2.dist-info/top_level.txt
