Metadata-Version: 2.0
Name: example-pkg-zzy
Version: 0.0.2
Summary: Template_package
Home-page: https://github.com/pypa/sampleproject
Author: 824zzy
Author-email: zhuzhengyuan824@gmail.com
License: UNKNOWN
Platform: UNKNOWN
Classifier: Programming Language :: Python :: 3
Classifier: License :: OSI Approved :: MIT License
Classifier: Operating System :: OS Independent
Requires-Dist: tqdm
